mkdocs_build_webhook/__init__.py
mkdocs_build_webhook/__main__.py
mkdocs_build_webhook/config.py
mkdocs_build_webhook-0.1.14.dist-info/METADATA
mkdocs_build_webhook-0.1.14.dist-info/WHEEL
mkdocs_build_webhook-0.1.14.dist-info/entry_points.txt
mkdocs_build_webhook-0.1.14.dist-info/RECORD
