Metadata-Version: 2.1
Name: mkdocs-build-webhook
Version: 0.1.14
Summary: 
Author: RincewindWizzard
Author-email: git@magierdinge.de
Requires-Python: >=3.10,<4.0
Classifier: Programming Language :: Python :: 3
Classifier: Programming Language :: Python :: 3.10
Classifier: Programming Language :: Python :: 3.11
Classifier: Programming Language :: Python :: 3.12
Requires-Dist: flask (>=3.0.2,<4.0.0)
Requires-Dist: gitpython (>=3.1.42,<4.0.0)
Requires-Dist: gunicorn (>=21.2.0,<22.0.0)
Requires-Dist: loguru (>=0.7.2,<0.8.0)
Requires-Dist: mkdocs (>=1.5.3,<2.0.0)
Requires-Dist: pytest (>=8.1.1,<9.0.0)
Requires-Dist: python-dotenv (>=1.0.1,<2.0.0)
Requires-Dist: toml (>=0.10.2,<0.11.0)
